zdt/__init__.py
zdt/connector_utils.py
zdt/country_map_master.py
zdt/hana_connector_utils.py
zdt/log_func.py
zdt/random_utils.py
zdt/time_func.py
zdt-2.7.8.dist-info/METADATA
zdt-2.7.8.dist-info/WHEEL
zdt-2.7.8.dist-info/top_level.txt
zdt-2.7.8.dist-info/RECORD
