Metadata-Version: 2.1
Name: zdt
Version: 2.7.8
Summary: zdt
Home-page: UNKNOWN
Author: Dickson
Author-email: <suwon2912@gmail.com>
License: UNKNOWN
Keywords: python
Platform: UNKNOWN
Classifier: Development Status :: 1 - Planning
Classifier: Intended Audience :: Developers
Classifier: Programming Language :: Python :: 3
Classifier: Operating System :: Unix
Classifier: Operating System :: MacOS :: MacOS X
Classifier: Operating System :: Microsoft :: Windows
Requires-Dist: sqlalchemy
Requires-Dist: typing
Requires-Dist: hdbcli
Requires-Dist: redmail
Requires-Dist: pandas (>=1.1)
Requires-Dist: datetime
Requires-Dist: python-dateutil
Requires-Dist: numpy
Requires-Dist: apache-airflow
Requires-Dist: azure-storage-file-datalake
